PSL_Tracer/Tracer_A.py
PSL_Tracer/Tracer_B.py
PSL_Tracer/Tracer_C.py
PSL_Tracer/__init__.py
psl_tracer-0.1.8.dist-info/licenses/LICENSE.txt
psl_tracer-0.1.8.dist-info/METADATA
psl_tracer-0.1.8.dist-info/WHEEL
psl_tracer-0.1.8.dist-info/top_level.txt
psl_tracer-0.1.8.dist-info/RECORD
